admm/__init__.py
admm/admm_problem.py
admm/assign.py
admm/boolean.py
admm/card.py
admm/choose.py
admm/integer.py
admm/noncvx_variable.py
ncvx/__init__.py
ncvx/admm_problem.py
ncvx/annulus.py
ncvx/assign.py
ncvx/boolean.py
ncvx/card.py
ncvx/choose.py
ncvx/group_assign.py
ncvx/integer.py
ncvx/noncvx_variable.py
ncvx/orthog.py
ncvx/partition.py
ncvx/rank.py
ncvx/soc_boundary.py
ncvx/sphere.py
ncvx/tour.py
noncvx_admm/__init__.py
noncvx_admm/admm_problem.py
noncvx_admm/annulus.py
noncvx_admm/assign.py
noncvx_admm/boolean.py
noncvx_admm/card.py
noncvx_admm/choose.py
noncvx_admm/extr_ball.py
noncvx_admm/integer.py
noncvx_admm/noncvx_variable.py
noncvx_admm/orthog.py
noncvx_admm/partition.py
noncvx_admm/rank.py
noncvx_admm/soc_boundary.py
noncvx_admm/sphere.py
noncvx_admm/tour.py
ncvx-0.1.9.dist-info/LICENSE
ncvx-0.1.9.dist-info/METADATA
ncvx-0.1.9.dist-info/WHEEL
ncvx-0.1.9.dist-info/pbr.json
ncvx-0.1.9.dist-info/top_level.txt
ncvx-0.1.9.dist-info/RECORD
